grid2viz/__init__.py
grid2viz/app.py
grid2viz/app_heroku.py
grid2viz/app_jupyter.py
grid2viz/assets/favicon.ico
grid2viz/assets/gif/Scenario_april_018_wk1_robustness_track.gif
grid2viz/assets/gif/Scenario_aug_07_adaptability_track.gif
grid2viz/assets/loader.gif
grid2viz/assets/loading.css
grid2viz/assets/main.css
grid2viz/assets/screenshots/agent_overview.png
grid2viz/assets/screenshots/agent_study.png
grid2viz/assets/screenshots/scenario_overview.png
grid2viz/assets/screenshots/scenario_selection.png
grid2viz/config_example.ini
grid2viz/config_icaps_val.ini
grid2viz/data/agents/alarm-baseline/000/_parameters.json
grid2viz/data/agents/alarm-baseline/000/actions.npz
grid2viz/data/agents/alarm-baseline/000/agent_exec_times.npz
grid2viz/data/agents/alarm-baseline/000/disc_lines_cascading_failure.npz
grid2viz/data/agents/alarm-baseline/000/env_modifications.npz
grid2viz/data/agents/alarm-baseline/000/episode_meta.json
grid2viz/data/agents/alarm-baseline/000/episode_times.json
grid2viz/data/agents/alarm-baseline/000/grid2op.info
grid2viz/data/agents/alarm-baseline/000/observations.npz
grid2viz/data/agents/alarm-baseline/000/opponent_attack.npz
grid2viz/data/agents/alarm-baseline/000/other_rewards.json
grid2viz/data/agents/alarm-baseline/000/rewards.npz
grid2viz/data/agents/alarm-baseline/dict_action_space.json
grid2viz/data/agents/alarm-baseline/dict_attack_space.json
grid2viz/data/agents/alarm-baseline/dict_env_modification_space.json
grid2viz/data/agents/alarm-baseline/dict_observation_space.json
grid2viz/data/agents/do-nothing-baseline/000/_parameters.json
grid2viz/data/agents/do-nothing-baseline/000/actions.npz
grid2viz/data/agents/do-nothing-baseline/000/agent_exec_times.npz
grid2viz/data/agents/do-nothing-baseline/000/disc_lines_cascading_failure.npz
grid2viz/data/agents/do-nothing-baseline/000/env_modifications.npz
grid2viz/data/agents/do-nothing-baseline/000/episode_meta.json
grid2viz/data/agents/do-nothing-baseline/000/episode_times.json
grid2viz-1.4.1.post1.dist-info/WHEEL
grid2viz-1.4.1.post1.dist-info/LICENSE
grid2viz-1.4.1.post1.dist-info/entry_points.txt
grid2viz-1.4.1.post1.dist-info/METADATA
grid2viz-1.4.1.post1.dist-info/RECORD
