Metadata-Version: 2.1
Name: grid2viz
Version: 1.4.1.post1
Summary: Grid2Op Visualization companion app.
License: MPL
Author: Mario Jothy
Author-email: mario.jothy@artelys.com
Requires-Python: >=3.7,<4.0
Classifier: Development Status :: 4 - Beta
Classifier: Intended Audience :: Developers
Classifier: Intended Audience :: Education
Classifier: Intended Audience :: Science/Research
Classifier: License :: OSI Approved :: Mozilla Public License 2.0 (MPL 2.0)
Classifier: License :: Other/Proprietary License
Classifier: Natural Language :: English
Classifier: Programming Language :: Python :: 3
Classifier: Programming Language :: Python :: 3.7
Classifier: Programming Language :: Python :: 3.8
Classifier: Programming Language :: Python :: 3.9
Classifier: Programming Language :: Python :: 3.10
Classifier: Programming Language :: Python :: 3.11
Classifier: Programming Language :: Python :: 3.6
Classifier: Programming Language :: Python :: 3.7
Provides-Extra: docs
Provides-Extra: expertsystem
Provides-Extra: jupyter-dash
Provides-Extra: jupyter-server-proxy
Provides-Extra: nbgitpuller
Requires-Dist: ExpertOp4grid (>=0.1.3,<0.2.0) ; extra == "expertsystem"
Requires-Dist: Grid2Op (>=1.7.1,<2.0.0)
Requires-Dist: click (>=7.1.2,<8.0.0)
Requires-Dist: colorama (>=0.4.4,<0.5.0)
Requires-Dist: dash-antd-components (>=0.0.1-rc.2,<0.0.2)
Requires-Dist: dash-bootstrap-components (>=1.0.1,<2.0.0)
Requires-Dist: dash-daq (>=0.5.0,<0.6.0)
Requires-Dist: dash[testing] (>=2.5.0,<3.0.0)
Requires-Dist: dill (>=0.3.3,<0.4.0)
Requires-Dist: gunicorn (>=20.0.4,<21.0.0)
Requires-Dist: imageio (>=2.9.0,<3.0.0)
Requires-Dist: jupyter-dash (>=0.3.1,<0.4.0) ; extra == "jupyter-dash"
Requires-Dist: jupyter-server-proxy (>=1.5.0,<2.0.0) ; extra == "jupyter-server-proxy"
Requires-Dist: matplotlib (>=3.3.3,<4.0.0)
Requires-Dist: nbgitpuller (>=0.9.0,<0.10.0) ; extra == "nbgitpuller"
Requires-Dist: numpy (>=1.22.0,<2.0.0)
Requires-Dist: pandapower (>=2.2.0,<3.0.0)
Requires-Dist: pathos (>=0.2.7,<0.3.0)
Requires-Dist: seaborn (>=0.11.0,<0.12.0)
